openai_promptify.py
openai_promptify_py-0.0.5.dist-info/METADATA
openai_promptify_py-0.0.5.dist-info/WHEEL
openai_promptify_py-0.0.5.dist-info/top_level.txt
openai_promptify_py-0.0.5.dist-info/RECORD
