Metadata-Version: 2.1
Name: openai-promptify-py
Version: 0.0.5
Summary: a utility wrapepr for openai calls [NOT OFFICIAL]
Project-URL: Homepage, https://github.com/tumatrix/openai-promptify-py.git/README.md
Classifier: Programming Language :: Python :: 3
Classifier: Operating System :: OS Independent
Requires-Python: >=3.9
Requires-Dist: openai >=0.27.8
